streamlit_state_model/__init__.py
streamlit_state_model/default_factory.py
streamlit_state_model/state_model.py
streamlit_state_model-0.1.1.dist-info/LICENSE
streamlit_state_model-0.1.1.dist-info/WHEEL
streamlit_state_model-0.1.1.dist-info/METADATA
streamlit_state_model-0.1.1.dist-info/RECORD
