Metadata-Version: 2.1
Name: streamlit-state-model
Version: 0.1.1
Summary: A package that provides a StateModel for Streamlit applications, allowing easy management of session state through class attributes.
Keywords: streamlit,state,model,session_state
Author-email: Trenton Smith <trenton@databutsmart.com>
Requires-Python: >=3.8
Classifier: Development Status :: 3 - Alpha
Classifier: Intended Audience :: Developers
Classifier: License :: OSI Approved :: MIT License
Classifier: Programming Language :: Python :: 3
Classifier: Programming Language :: Python :: 3.8
Classifier: Programming Language :: Python :: 3.9
Classifier: Programming Language :: Python :: 3.10
Project-URL: Documentation, https://github.com/trenton-ftw/streamlit-state-model#readme
Project-URL: Homepage, https://github.com/trenton-ftw/streamlit-state-model
Project-URL: Source, https://github.com/trenton-ftw/streamlit-state-model
Project-URL: Tracker, https://github.com/trenton-ftw/streamlit-state-model/issues
